{
  "build": {
    "dockerfile": "Dockerfile",
    "context": ".",
    "args": {
      "USERNAME": "dev",
      "REPO": "/ws"
    }
  },
  "containerUser": "dev",
  "remoteUser": "dev",
  "runArgs": [
    "--env-file",
    "../.env"
  ],
  "workspaceMount": "source=${localWorkspaceFolder}/../,target=/ws,type=bind,consistency=cached",
  "workspaceFolder": "/ws",
  "customizations": {
    "vscode": {
      "extensions": [
        "tamasfe.even-better-toml",
        "rust-lang.rust-analyzer",
        "fill-labs.dependi"
      ]
    }
  }
}